MANIFEST.in
README.md
requirements.txt
setup.py
naiveBayesClassifier/ExceptionNotSeen.py
naiveBayesClassifier/__init__.py
naiveBayesClassifier/classifier.py
naiveBayesClassifier/tokenizer.py
naiveBayesClassifier/trainedData.py
naiveBayesClassifier/trainer.py
naiveBayesClassifier.egg-info/PKG-INFO
naiveBayesClassifier.egg-info/SOURCES.txt
naiveBayesClassifier.egg-info/dependency_links.txt
naiveBayesClassifier.egg-info/top_level.txt