Metadata-Version: 1.0
Name: naiveBayesClassifier
Version: 0.1.3
Summary: yet another general purpose naive bayesian classifier
Home-page: https://github.com/muatik/naive-bayes-classifier
Author: Nejdet Yucesoy
Author-email: nejdetyucesoy@gmail.com
License: MIT
Platform: any
